LICENSE
j2dx/__init__.py
j2dx/nix/device.py
j2dx/nix/setup.py
j2dx/win/ViGEm/client.py
j2dx/win/ViGEm/x64/ViGEmClient.dll
j2dx/win/ViGEm/x64/__init__.py
j2dx/win/ViGEm/x86/ViGEmClient.dll
j2dx/win/ViGEm/x86/__init__.py
j2dx/win/device.py
j2dx/win/setup.py
j2dx-0.1.0.dist-info/entry_points.txt
j2dx-0.1.0.dist-info/LICENSE
j2dx-0.1.0.dist-info/WHEEL
j2dx-0.1.0.dist-info/METADATA
j2dx-0.1.0.dist-info/RECORD
