Metadata-Version: 2.1
Name: j2dx
Version: 0.1.0
Summary: Use your Android phone as a virtual Xbox 360 controller or DualShock 4 gamepad on your Windows or Linux PC. This is the server that runs on Windows or Linux.
Home-page: https://github.com/OzymandiasTheGreat/Joy2DroidX-server
License: GPL-3.0
Keywords: virtual-device,gamepad,controller
Author: Tomas Ravinskas
Author-email: tomas.rav@gmail.com
Requires-Python: >=3.7,<4.0
Classifier: Environment :: Console
Classifier: Intended Audience :: End Users/Desktop
Classifier: License :: OSI Approved :: GNU General Public License v3 (GPLv3)
Classifier: Operating System :: Microsoft :: Windows :: Windows 10
Classifier: Operating System :: POSIX :: Linux
Classifier: Programming Language :: Python :: 3
Classifier: Programming Language :: Python :: 3.7
Classifier: Topic :: Games/Entertainment
Classifier: Topic :: System :: Emulators
Requires-Dist: colorama (>=0.4,<0.5); sys_platform == "win32"
Requires-Dist: evdev (>=1.2,<2.0); sys_platform == "linux"
Requires-Dist: eventlet (>=0.25,<0.26)
Requires-Dist: python-socketio (>=4.2,<5.0)
Requires-Dist: qrcode (>=6.1,<7.0)
Project-URL: Repository, https://github.com/OzymandiasTheGreat/Joy2DroidX-server
